HSEyeUtils/Extraction.py
HSEyeUtils/Visualizer.py
HSEyeUtils/__init__.py
HSEyeUtils-0.0.2.dist-info/METADATA
HSEyeUtils-0.0.2.dist-info/WHEEL
HSEyeUtils-0.0.2.dist-info/top_level.txt
HSEyeUtils-0.0.2.dist-info/RECORD
